perfetto_extras/__init__.py
perfetto_extras/__main__.py
perfetto_extras/opentrace.py
perfetto_extras/trace_events.py
perfetto_extras-0.3.4.dist-info/METADATA
perfetto_extras-0.3.4.dist-info/WHEEL
perfetto_extras-0.3.4.dist-info/entry_points.txt
perfetto_extras-0.3.4.dist-info/RECORD
