Metadata-Version: 2.3
Name: perfetto_extras
Version: 0.3.4
Summary: 
Author: merlotliu
Author-email: meetlouisliu@163.com
Requires-Python: >=3.11
Classifier: Programming Language :: Python :: 3
Classifier: Programming Language :: Python :: 3.11
Classifier: Programming Language :: Python :: 3.12
Classifier: Programming Language :: Python :: 3.13
Requires-Dist: click (>=7.0)
Requires-Dist: protobuf (==5.29.3)
